mtg_parser/__init__.py
mtg_parser/aetherhub.py
mtg_parser/archidekt.py
mtg_parser/card.py
mtg_parser/deck_parser.py
mtg_parser/decklist.py
mtg_parser/deckstats.py
mtg_parser/grammar.py
mtg_parser/http_client.py
mtg_parser/moxfield.py
mtg_parser/mtggoldfish.py
mtg_parser/mtgjson.py
mtg_parser/parser.py
mtg_parser/scryfall.py
mtg_parser/tappedout.py
mtg_parser/tcgplayer.py
mtg_parser/utils.py
mtg_parser-0.0.1a50.dist-info/METADATA
mtg_parser-0.0.1a50.dist-info/WHEEL
mtg_parser-0.0.1a50.dist-info/licenses/LICENSE
mtg_parser-0.0.1a50.dist-info/RECORD
