Metadata-Version: 2.4
Name: mtg_parser
Version: 0.0.1a50
Summary: Magic: the Gathering decklist parser
License-Expression: EUPL-1.2
License-File: LICENSE
Author: Ludovic Heyberger
Author-email: 940408+lheyberger@users.noreply.github.com
Requires-Python: >=3.9
Classifier: Programming Language :: Python :: 3
Classifier: Programming Language :: Python :: 3.9
Classifier: Programming Language :: Python :: 3.10
Classifier: Programming Language :: Python :: 3.11
Classifier: Programming Language :: Python :: 3.12
Classifier: Programming Language :: Python :: 3.13
Classifier: Programming Language :: Python :: 3.14
Requires-Dist: beautifulsoup4 (>=4.12,<5.0)
Requires-Dist: pyparsing (>=3.1,<4.0)
Project-URL: Documentation, https://github.com/lheyberger/mtg-parser
Project-URL: Homepage, https://github.com/lheyberger/mtg-parser
Project-URL: Repository, https://github.com/lheyberger/mtg-parser
